api/__init__.py
api/main.py
pyfeed/__init__.py
pyfeed/_utils.py
pyfeed/cli.py
pyfeed/feed.py
pyfeed/filtering.py
pyfeed/merge.py
pyfeed/parser.py
pyfeed-0.1.1.dist-info/licenses/LICENSE
pyfeed-0.1.1.dist-info/METADATA
pyfeed-0.1.1.dist-info/WHEEL
pyfeed-0.1.1.dist-info/entry_points.txt
pyfeed-0.1.1.dist-info/top_level.txt
pyfeed-0.1.1.dist-info/RECORD
