Metadata-Version: 2.4
Name: pyfeed
Version: 0.1.1
Summary: Pure Python RSS/Atom parser and feed backend API
Author-email: Joey <you@example.com>
License-Expression: MIT
Requires-Python: >=3.8
License-File: LICENSE
Requires-Dist: fastapi
Requires-Dist: uvicorn
Requires-Dist: python-dateutil
Dynamic: license-file
